{"image_id": 688, "annotations": [{"oid": 0, "pos": [329, 536], "instances": [{"iid": 0, "pos": [981, 517], "direct": true, "rear": false}, {"iid": 1, "pos": [918, 523], "direct": false, "rear": false}, {"iid": 2, "pos": [473, 513], "direct": false, "rear": false}, {"iid": 3, "pos": [970, 517], "direct": true, "rear": false}], "direct": false}, {"oid": 1, "pos": [336, 540], "instances": [{"iid": 0, "pos": [1063, 518], "direct": true, "rear": false}, {"iid": 1, "pos": [1073, 519], "direct": true, "rear": false}, {"iid": 2, "pos": [1012, 524], "direct": false, "rear": false}], "direct": false}]}