{"image_id": 5680, "annotations": [{"oid": 0, "pos": [475, 567], "instances": [{"iid": 0, "pos": [469, 561], "direct": true, "rear": false}, {"iid": 1, "pos": [484, 561], "direct": true, "rear": false}, {"iid": 5, "pos": [389, 552], "direct": false, "rear": false}], "direct": true}, {"oid": 1, "pos": [505, 568], "instances": [{"iid": 0, "pos": [501, 567], "direct": true, "rear": true}, {"iid": 1, "pos": [511, 567], "direct": true, "rear": true}, {"iid": 2, "pos": [506, 563], "direct": true, "rear": true}], "direct": true}]}