{"image_id": 11383, "annotations": [{"oid": 0, "pos": [159, 760], "instances": [{"iid": 0, "pos": [72, 666], "direct": true, "rear": false}, {"iid": 1, "pos": [244, 673], "direct": true, "rear": false}, {"iid": 4, "pos": [225, 806], "direct": false, "rear": false}], "direct": true}, {"oid": 1, "pos": [613, 581], "instances": [{"iid": 0, "pos": [590, 556], "direct": true, "rear": false}, {"iid": 1, "pos": [638, 559], "direct": true, "rear": false}, {"iid": 2, "pos": [631, 607], "direct": false, "rear": false}], "direct": true}], "blurs": [[116, 695, 192, 713]]}