{"image_id": 23197, "annotations": [{"oid": 0, "pos": [362, 482], "instances": [{"iid": 1, "pos": [356, 478], "direct": true, "rear": false}, {"iid": 2, "pos": [367, 478], "direct": true, "rear": false}], "direct": false}, {"oid": 1, "pos": [364, 483], "instances": [{"iid": 1, "pos": [311, 471], "direct": true, "rear": false}, {"iid": 2, "pos": [321, 471], "direct": true, "rear": false}], "direct": false}, {"oid": 2, "pos": [360, 484], "instances": [{"iid": 0, "pos": [245, 458], "direct": true, "rear": false}, {"iid": 1, "pos": [251, 459], "direct": true, "rear": false}], "direct": false}]}