{"image_id": 23239, "annotations": [{"oid": 0, "pos": [384, 485], "instances": [{"iid": 1, "pos": [376, 481], "direct": true, "rear": false}, {"iid": 2, "pos": [390, 482], "direct": true, "rear": false}, {"iid": 3, "pos": [376, 491], "direct": false, "rear": false}, {"iid": 4, "pos": [389, 490], "direct": false, "rear": false}], "direct": true}, {"oid": 1, "pos": [326, 474], "instances": [{"iid": 1, "pos": [320, 472], "direct": true, "rear": false}, {"iid": 2, "pos": [333, 471], "direct": true, "rear": false}, {"iid": 3, "pos": [320, 478], "direct": false, "rear": false}, {"iid": 4, "pos": [333, 478], "direct": false, "rear": false}], "direct": false}, {"oid": 2, "pos": [228, 454], "instances": [{"iid": 0, "pos": [225, 451], "direct": true, "rear": false}, {"iid": 1, "pos": [231, 452], "direct": true, "rear": false}], "direct": false}]}