{"image_id": 25548, "annotations": [{"oid": 0, "pos": [658, 496], "instances": [{"iid": 1, "pos": [642, 486], "direct": true, "rear": false}, {"iid": 2, "pos": [673, 484], "direct": true, "rear": false}, {"iid": 3, "pos": [641, 449], "direct": true, "rear": false}, {"iid": 4, "pos": [672, 446], "direct": true, "rear": false}, {"iid": 6, "pos": [674, 543], "direct": false, "rear": false}, {"iid": 7, "pos": [641, 547], "direct": false, "rear": false}], "direct": true}, {"oid": 1, "pos": [656, 511], "instances": [{"iid": 0, "pos": [425, 475], "direct": true, "rear": true}, {"iid": 1, "pos": [436, 475], "direct": true, "rear": true}, {"iid": 2, "pos": [412, 480], "direct": false, "rear": true}], "direct": false}]}