{"image_id": 27826, "annotations": [{"oid": 0, "pos": [585, 496], "instances": [{"iid": 0, "pos": [577, 490], "direct": true, "rear": false}, {"iid": 1, "pos": [596, 490], "direct": true, "rear": false}, {"iid": 2, "pos": [524, 488], "direct": false, "rear": false}, {"iid": 3, "pos": [576, 504], "direct": false, "rear": false}, {"iid": 4, "pos": [596, 505], "direct": false, "rear": false}], "direct": true}, {"oid": 1, "pos": [589, 496], "instances": [{"iid": 0, "pos": [1238, 445], "direct": true, "rear": false}, {"iid": 1, "pos": [1241, 445], "direct": true, "rear": false}], "direct": false}]}