{"image_id": 29518, "annotations": [{"oid": 1, "pos": [689, 544], "instances": [{"iid": 0, "pos": [677, 533], "direct": true, "rear": false}, {"iid": 1, "pos": [705, 533], "direct": true, "rear": false}, {"iid": 2, "pos": [677, 556], "direct": false, "rear": false}, {"iid": 3, "pos": [705, 556], "direct": false, "rear": false}], "direct": true}, {"oid": 2, "pos": [847, 538], "instances": [{"iid": 0, "pos": [1178, 500], "direct": true, "rear": false}, {"iid": 1, "pos": [1186, 500], "direct": true, "rear": false}], "direct": false}, {"oid": 3, "pos": [849, 536], "instances": [{"iid": 0, "pos": [1208, 482], "direct": true, "rear": false}, {"iid": 1, "pos": [1214, 481], "direct": true, "rear": false}], "direct": false}, {"oid": 4, "pos": [847, 538], "instances": [{"iid": 0, "pos": [1188, 479], "direct": true, "rear": false}, {"iid": 1, "pos": [1198, 478], "direct": true, "rear": false}, {"iid": 2, "pos": [1187, 467], "direct": true, "rear": false}, {"iid": 3, "pos": [1196, 466], "direct": true, "rear": false}], "direct": false}, {"oid": 5, "pos": [848, 536], "instances": [{"iid": 0, "pos": [1109, 466], "direct": true, "rear": false}, {"iid": 1, "pos": [1113, 466], "direct": true, "rear": false}], "direct": false}, {"oid": 6, "pos": [847, 536], "instances": [{"iid": 0, "pos": [1102, 464], "direct": true, "rear": false}, {"iid": 1, "pos": [1105, 464], "direct": true, "rear": false}], "direct": false}]}