{"image_id": 31698, "annotations": [{"oid": 0, "pos": [591, 541], "instances": [{"iid": 0, "pos": [579, 533], "direct": true, "rear": false}, {"iid": 1, "pos": [604, 534], "direct": true, "rear": false}, {"iid": 2, "pos": [580, 506], "direct": true, "rear": false}, {"iid": 4, "pos": [594, 511], "direct": true, "rear": false}, {"iid": 5, "pos": [604, 507], "direct": true, "rear": false}, {"iid": 6, "pos": [579, 549], "direct": false, "rear": false}, {"iid": 7, "pos": [604, 549], "direct": false, "rear": false}, {"iid": 8, "pos": [561, 536], "direct": false, "rear": false}, {"iid": 9, "pos": [547, 544], "direct": false, "rear": false}], "direct": true}]}