{"image_id": 47162, "annotations": [{"oid": 0, "pos": [602, 514], "instances": [{"iid": 0, "pos": [596, 508], "direct": true, "rear": false}, {"iid": 1, "pos": [610, 509], "direct": true, "rear": false}, {"iid": 2, "pos": [594, 517], "direct": false, "rear": false}, {"iid": 3, "pos": [609, 518], "direct": false, "rear": false}], "direct": true}, {"oid": 1, "pos": [643, 511], "instances": [{"iid": 0, "pos": [639, 508], "direct": true, "rear": false}, {"iid": 1, "pos": [647, 508], "direct": true, "rear": false}, {"iid": 2, "pos": [639, 513], "direct": false, "rear": false}, {"iid": 3, "pos": [648, 513], "direct": false, "rear": false}], "direct": true}, {"oid": 2, "pos": [658, 512], "instances": [{"iid": 0, "pos": [655, 510], "direct": true, "rear": false}, {"iid": 1, "pos": [662, 510], "direct": true, "rear": false}], "direct": true}, {"oid": 3, "pos": [671, 515], "instances": [{"iid": 0, "pos": [668, 513], "direct": true, "rear": false}, {"iid": 1, "pos": [673, 513], "direct": true, "rear": false}], "direct": true}]}