{"image_id": 96086, "annotations": [{"oid": 0, "pos": [473, 577], "instances": [{"iid": 0, "pos": [411, 534], "direct": true, "rear": false}, {"iid": 1, "pos": [536, 531], "direct": true, "rear": false}, {"iid": 2, "pos": [415, 400], "direct": true, "rear": false}, {"iid": 3, "pos": [529, 396], "direct": true, "rear": false}, {"iid": 4, "pos": [413, 621], "direct": false, "rear": false}, {"iid": 5, "pos": [536, 625], "direct": false, "rear": false}, {"iid": 7, "pos": [247, 597], "direct": false, "rear": false}], "direct": true}, {"oid": 1, "pos": [688, 516], "instances": [{"iid": 0, "pos": [672, 500], "direct": true, "rear": false}, {"iid": 1, "pos": [708, 499], "direct": true, "rear": false}, {"iid": 2, "pos": [672, 538], "direct": false, "rear": false}, {"iid": 3, "pos": [707, 530], "direct": false, "rear": false}], "direct": true}], "blurs": [[408, 407, 443, 426], [455, 404, 513, 425]]}