{"image_id": 97255, "annotations": [{"oid": 0, "pos": [723, 569], "instances": [{"iid": 0, "pos": [709, 555], "direct": true, "rear": false}, {"iid": 1, "pos": [739, 555], "direct": true, "rear": false}, {"iid": 2, "pos": [710, 572], "direct": false, "rear": false}, {"iid": 3, "pos": [739, 574], "direct": false, "rear": false}, {"iid": 4, "pos": [588, 561], "direct": false, "rear": false}], "direct": true}, {"oid": 1, "pos": [808, 567], "instances": [{"iid": 0, "pos": [847, 553], "direct": true, "rear": false}, {"iid": 2, "pos": [848, 565], "direct": false, "rear": false}], "direct": false}, {"oid": 2, "pos": [808, 568], "instances": [{"iid": 0, "pos": [870, 549], "direct": true, "rear": false}, {"iid": 1, "pos": [883, 549], "direct": true, "rear": false}, {"iid": 2, "pos": [883, 563], "direct": false, "rear": false}], "direct": false}]}