{"image_id": 97261, "annotations": [{"oid": 0, "pos": [703, 566], "instances": [{"iid": 0, "pos": [688, 553], "direct": true, "rear": false}, {"iid": 1, "pos": [720, 553], "direct": true, "rear": false}, {"iid": 2, "pos": [688, 571], "direct": false, "rear": false}, {"iid": 3, "pos": [720, 575], "direct": false, "rear": false}, {"iid": 4, "pos": [556, 560], "direct": false, "rear": false}], "direct": true}, {"oid": 1, "pos": [811, 567], "instances": [{"iid": 0, "pos": [835, 551], "direct": true, "rear": false}, {"iid": 1, "pos": [851, 551], "direct": true, "rear": false}, {"iid": 2, "pos": [834, 564], "direct": false, "rear": false}, {"iid": 3, "pos": [851, 564], "direct": false, "rear": false}], "direct": false}, {"oid": 2, "pos": [811, 567], "instances": [{"iid": 0, "pos": [859, 547], "direct": true, "rear": false}, {"iid": 1, "pos": [872, 547], "direct": true, "rear": false}], "direct": false}]}