{"image_id": 97299, "annotations": [{"oid": 0, "pos": [512, 595], "instances": [{"iid": 0, "pos": [474, 560], "direct": true, "rear": false}, {"iid": 1, "pos": [544, 560], "direct": true, "rear": false}, {"iid": 2, "pos": [471, 603], "direct": false, "rear": false}], "direct": true}, {"oid": 1, "pos": [752, 557], "instances": [{"iid": 0, "pos": [740, 546], "direct": true, "rear": false}, {"iid": 1, "pos": [765, 546], "direct": true, "rear": false}, {"iid": 2, "pos": [740, 563], "direct": false, "rear": false}, {"iid": 3, "pos": [764, 564], "direct": false, "rear": false}], "direct": true}, {"oid": 2, "pos": [780, 547], "instances": [{"iid": 0, "pos": [771, 539], "direct": true, "rear": false}, {"iid": 1, "pos": [789, 539], "direct": true, "rear": false}, {"iid": 2, "pos": [774, 552], "direct": false, "rear": false}, {"iid": 3, "pos": [790, 553], "direct": false, "rear": false}], "direct": true}]}