{"image_id": 98478, "annotations": [{"oid": 0, "pos": [676, 565], "instances": [{"iid": 0, "pos": [649, 535], "direct": true, "rear": false}, {"iid": 1, "pos": [709, 535], "direct": true, "rear": false}, {"iid": 2, "pos": [648, 583], "direct": false, "rear": false}, {"iid": 3, "pos": [712, 590], "direct": false, "rear": false}, {"iid": 6, "pos": [648, 545], "direct": true, "rear": false}, {"iid": 7, "pos": [709, 545], "direct": true, "rear": false}], "direct": true}, {"oid": 1, "pos": [810, 533], "instances": [{"iid": 0, "pos": [795, 522], "direct": true, "rear": false}, {"iid": 1, "pos": [825, 522], "direct": true, "rear": false}, {"iid": 2, "pos": [796, 541], "direct": false, "rear": false}, {"iid": 3, "pos": [825, 542], "direct": false, "rear": false}, {"iid": 5, "pos": [796, 527], "direct": true, "rear": false}, {"iid": 6, "pos": [821, 527], "direct": true, "rear": false}], "direct": true}, {"oid": 2, "pos": [848, 529], "instances": [{"iid": 0, "pos": [839, 522], "direct": true, "rear": false}, {"iid": 1, "pos": [858, 522], "direct": true, "rear": false}, {"iid": 2, "pos": [838, 532], "direct": false, "rear": false}, {"iid": 3, "pos": [856, 534], "direct": false, "rear": false}], "direct": true}]}