{"image_id": 98484, "annotations": [{"oid": 0, "pos": [612, 583], "instances": [{"iid": 0, "pos": [581, 550], "direct": true, "rear": false}, {"iid": 1, "pos": [652, 550], "direct": true, "rear": false}, {"iid": 2, "pos": [581, 615], "direct": false, "rear": false}, {"iid": 3, "pos": [656, 617], "direct": false, "rear": false}, {"iid": 6, "pos": [581, 562], "direct": true, "rear": false}, {"iid": 7, "pos": [651, 562], "direct": true, "rear": false}], "direct": true}, {"oid": 1, "pos": [769, 545], "instances": [{"iid": 0, "pos": [753, 532], "direct": true, "rear": false}, {"iid": 1, "pos": [785, 532], "direct": true, "rear": false}, {"iid": 2, "pos": [754, 553], "direct": false, "rear": false}, {"iid": 3, "pos": [786, 553], "direct": false, "rear": false}, {"iid": 5, "pos": [755, 537], "direct": true, "rear": false}, {"iid": 6, "pos": [782, 538], "direct": true, "rear": false}], "direct": true}, {"oid": 2, "pos": [809, 538], "instances": [{"iid": 0, "pos": [800, 531], "direct": true, "rear": false}, {"iid": 1, "pos": [819, 532], "direct": true, "rear": false}, {"iid": 2, "pos": [799, 543], "direct": false, "rear": false}, {"iid": 3, "pos": [819, 544], "direct": false, "rear": false}], "direct": true}]}